aglite_test.tabular-0.7.0b20230314-py3.10-nspkg.pth
autogluon/tabular/__init__.py
autogluon/tabular/version.py
autogluon/tabular/configs/__init__.py
autogluon/tabular/configs/config_helper.py
autogluon/tabular/configs/feature_generator_presets.py
autogluon/tabular/configs/hyperparameter_configs.py
autogluon/tabular/configs/presets_configs.py
autogluon/tabular/learner/__init__.py
autogluon/tabular/learner/abstract_learner.py
autogluon/tabular/learner/default_learner.py
autogluon/tabular/models/__init__.py
autogluon/tabular/models/_utils/__init__.py
autogluon/tabular/models/_utils/rapids_utils.py
autogluon/tabular/models/_utils/torch_utils.py
autogluon/tabular/models/automm/__init__.py
autogluon/tabular/models/automm/automm_model.py
autogluon/tabular/models/automm/ft_transformer.py
autogluon/tabular/models/catboost/__init__.py
autogluon/tabular/models/catboost/callbacks.py
autogluon/tabular/models/catboost/catboost_model.py
autogluon/tabular/models/catboost/catboost_softclass_utils.py
autogluon/tabular/models/catboost/catboost_utils.py
autogluon/tabular/models/catboost/hyperparameters/__init__.py
autogluon/tabular/models/catboost/hyperparameters/parameters.py
autogluon/tabular/models/catboost/hyperparameters/searchspaces.py
autogluon/tabular/models/fastainn/__init__.py
autogluon/tabular/models/fastainn/callbacks.py
autogluon/tabular/models/fastainn/fastai_helpers.py
autogluon/tabular/models/fastainn/imports_helper.py
autogluon/tabular/models/fastainn/quantile_helpers.py
autogluon/tabular/models/fastainn/tabular_nn_fastai.py
autogluon/tabular/models/fastainn/hyperparameters/__init__.py
autogluon/tabular/models/fastainn/hyperparameters/parameters.py
autogluon/tabular/models/fastainn/hyperparameters/searchspaces.py
autogluon/tabular/models/fasttext/__init__.py
autogluon/tabular/models/fasttext/fasttext_model.py
autogluon/tabular/models/fasttext/hyperparameters/__init__.py
autogluon/tabular/models/fasttext/hyperparameters/parameters.py
aglite_test.tabular-0.7.0b20230314.dist-info/METADATA
aglite_test.tabular-0.7.0b20230314.dist-info/WHEEL
aglite_test.tabular-0.7.0b20230314.dist-info/namespace_packages.txt
aglite_test.tabular-0.7.0b20230314.dist-info/top_level.txt
aglite_test.tabular-0.7.0b20230314.dist-info/zip-safe
aglite_test.tabular-0.7.0b20230314.dist-info/RECORD
