Metadata-Version: 2.1
Name: aglite-test.tabular
Version: 0.7.0b20230314
Summary: AutoML for Image, Text, and Tabular Data
Home-page: https://github.com/autogluon/autogluon
Author: AutoGluon Community
License: Apache-2.0
Project-URL: Documentation, https://auto.gluon.ai
Project-URL: Bug Reports, https://github.com/autogluon/autogluon/issues
Project-URL: Source, https://github.com/autogluon/autogluon/
Project-URL: Contribute!, https://github.com/autogluon/autogluon/blob/master/CONTRIBUTING.md
Classifier: Development Status :: 4 - Beta
Classifier: Intended Audience :: Education
Classifier: Intended Audience :: Developers
Classifier: Intended Audience :: Science/Research
Classifier: Intended Audience :: Customer Service
Classifier: Intended Audience :: Financial and Insurance Industry
Classifier: Intended Audience :: Healthcare Industry
Classifier: Intended Audience :: Telecommunications Industry
Classifier: License :: OSI Approved :: Apache Software License
Classifier: Operating System :: MacOS
Classifier: Operating System :: Microsoft :: Windows
Classifier: Operating System :: POSIX
Classifier: Operating System :: Unix
Classifier: Programming Language :: Python :: 3
Classifier: Programming Language :: Python :: 3.8
Classifier: Programming Language :: Python :: 3.9
Classifier: Programming Language :: Python :: 3.10
Classifier: Topic :: Software Development
Classifier: Topic :: Scientific/Engineering :: Artificial Intelligence
Classifier: Topic :: Scientific/Engineering :: Information Analysis
Classifier: Topic :: Scientific/Engineering :: Image Recognition
Requires-Python: >=3.8, <3.11
License-File: ../LICENSE
License-File: ../NOTICE
Requires-Dist: numpy (<1.27,>=1.21)
Requires-Dist: scipy (<1.12,>=1.5.4)
Requires-Dist: pandas (<1.6,>=1.4.1)
Requires-Dist: scikit-learn (<1.3,>=1.0)
Requires-Dist: networkx (<3.0,>=2.3)
Requires-Dist: aglite-test.core (==0.7.0b20230314)
Requires-Dist: aglite-test.features (==0.7.0b20230314)
Provides-Extra: all
Requires-Dist: xgboost (<1.8,>=1.6) ; extra == 'all'
Requires-Dist: torch (<1.14,>=1.9) ; extra == 'all'
Requires-Dist: fastai (<2.8,>=2.3.1) ; extra == 'all'
Requires-Dist: aglite-test.core[all] (==0.7.0b20230314) ; extra == 'all'
Requires-Dist: catboost (<1.2,>=1.0) ; extra == 'all'
Requires-Dist: lightgbm (<3.4,>=3.3) ; extra == 'all'
Provides-Extra: catboost
Requires-Dist: catboost (<1.2,>=1.0) ; extra == 'catboost'
Provides-Extra: fastai
Requires-Dist: torch (<1.14,>=1.9) ; extra == 'fastai'
Requires-Dist: fastai (<2.8,>=2.3.1) ; extra == 'fastai'
Provides-Extra: imodels
Requires-Dist: imodels (<1.4.0,>=1.3.10) ; extra == 'imodels'
Provides-Extra: lightgbm
Requires-Dist: lightgbm (<3.4,>=3.3) ; extra == 'lightgbm'
Provides-Extra: ray
Requires-Dist: aglite-test.core[all] (==0.7.0b20230314) ; extra == 'ray'
Provides-Extra: skex
Requires-Dist: scikit-learn-intelex (<2023.1,>=2021.7) ; extra == 'skex'
Provides-Extra: skl2onnx
Requires-Dist: skl2onnx (<1.14.0,>=1.13.0) ; extra == 'skl2onnx'
Requires-Dist: onnxruntime (<1.14.0,>=1.13.0) ; extra == 'skl2onnx'
Provides-Extra: tests
Requires-Dist: imodels (<1.4.0,>=1.3.10) ; extra == 'tests'
Requires-Dist: vowpalwabbit (<9.5,>=9) ; extra == 'tests'
Requires-Dist: skl2onnx (<1.14.0,>=1.13.0) ; extra == 'tests'
Requires-Dist: onnxruntime (<1.14.0,>=1.13.0) ; extra == 'tests'
Provides-Extra: vowpalwabbit
Requires-Dist: vowpalwabbit (<9.5,>=9) ; extra == 'vowpalwabbit'
Provides-Extra: xgboost
Requires-Dist: xgboost (<1.8,>=1.6) ; extra == 'xgboost'
